hep_ml/__init__.py
hep_ml/_version.py
hep_ml/commonutils.py
hep_ml/gradientboosting.py
hep_ml/losses.py
hep_ml/metrics.py
hep_ml/metrics_utils.py
hep_ml/preprocessing.py
hep_ml/reweight.py
hep_ml/speedup.py
hep_ml/splot.py
hep_ml/tree.py
hep_ml/uboost.py
hep_ml/experiments/README.md
hep_ml/experiments/__init__.py
hep_ml-0.8.0.dist-info/METADATA
hep_ml-0.8.0.dist-info/WHEEL
hep_ml-0.8.0.dist-info/licenses/LICENSE
hep_ml-0.8.0.dist-info/RECORD
