Metadata-Version: 2.4
Name: hep_ml
Version: 0.8.0
Summary: Machine Learning for High Energy Physics
Project-URL: Homepage, https://github.com/arogozhnikov/hep_ml
Author: Alex Rogozhnikov
License: Apache 2.0
License-File: LICENSE
Keywords: high energy physics,machine learning,particle physics,supervised learning,uncorrelated methods of machine learning
Classifier: Intended Audience :: Science/Research
Classifier: License :: OSI Approved :: Apache Software License
Requires-Python: >3.9
Requires-Dist: numpy>=1.9
Requires-Dist: pandas>=1.0.0
Requires-Dist: scikit-learn>=1.0
Requires-Dist: scipy>=1.0.0
Provides-Extra: dev
Requires-Dist: ipython[all]>=3.0; extra == 'dev'
Requires-Dist: matplotlib>=1.4; extra == 'dev'
Requires-Dist: nbval; extra == 'dev'
Requires-Dist: pre-commit; extra == 'dev'
Requires-Dist: pytest-cov; extra == 'dev'
Requires-Dist: pytest-xdist; extra == 'dev'
Requires-Dist: pytest>8; extra == 'dev'
Requires-Dist: ruff; extra == 'dev'
Requires-Dist: sphinx; extra == 'dev'
Requires-Dist: sphinx-rtd-theme; extra == 'dev'
Requires-Dist: uproot; extra == 'dev'
Provides-Extra: doc
Requires-Dist: sphinx; extra == 'doc'
Requires-Dist: sphinx-rtd-theme; extra == 'doc'
Requires-Dist: uproot; extra == 'doc'
Provides-Extra: test
Requires-Dist: ipython[all]>=3.0; extra == 'test'
Requires-Dist: matplotlib>=1.4; extra == 'test'
Requires-Dist: nbval; extra == 'test'
Requires-Dist: pytest-cov; extra == 'test'
Requires-Dist: pytest-xdist; extra == 'test'
Requires-Dist: pytest>8; extra == 'test'
